rubin_jupyter_utils/hub/__init__.py
rubin_jupyter_utils/hub/_version.py
rubin_jupyter_utils/hub/authenticator/__init__.py
rubin_jupyter_utils/hub/authenticator/rubinauthenticator.py
rubin_jupyter_utils/hub/authenticator/rubinwebtokenauthenticator.py
rubin_jupyter_utils/hub/authenticator/rubinwebtokenloginhandler.py
rubin_jupyter_utils/hub/loggable/__init__.py
rubin_jupyter_utils/hub/loggable/loggable.py
rubin_jupyter_utils/hub/loggable/loggablechild.py
rubin_jupyter_utils/hub/rubinmgr/__init__.py
rubin_jupyter_utils/hub/rubinmgr/apimanager.py
rubin_jupyter_utils/hub/rubinmgr/envmanager.py
rubin_jupyter_utils/hub/rubinmgr/middlemanager.py
rubin_jupyter_utils/hub/rubinmgr/namespacemanager.py
rubin_jupyter_utils/hub/rubinmgr/optionsformmanager.py
rubin_jupyter_utils/hub/rubinmgr/quotamanager.py
rubin_jupyter_utils/hub/rubinmgr/volumemanager.py
rubin_jupyter_utils/hub/scanrepo/__init__.py
rubin_jupyter_utils/hub/scanrepo/parse_args.py
rubin_jupyter_utils/hub/scanrepo/prepuller.py
rubin_jupyter_utils/hub/scanrepo/prepullerstandalone.py
rubin_jupyter_utils/hub/scanrepo/primerepocache.py
rubin_jupyter_utils/hub/scanrepo/reaper.py
rubin_jupyter_utils/hub/scanrepo/reaperstandalone.py
rubin_jupyter_utils/hub/scanrepo/scanrepo.py
rubin_jupyter_utils/hub/scanrepo/singletonscanner.py
rubin_jupyter_utils/hub/scanrepo/standalone.py
rubin_jupyter_utils/hub/spawner/__init__.py
rubin_jupyter_utils/hub/spawner/multireflector.py
rubin_jupyter_utils/hub/spawner/multispawner.py
rubin_jupyter_utils/hub/spawner/objects.py
rubin_jupyter_utils/hub/spawner/rubinspawner.py
rubin_jupyter_utils.hub-0.38.0.dist-info/LICENSE
rubin_jupyter_utils.hub-0.38.0.dist-info/METADATA
rubin_jupyter_utils.hub-0.38.0.dist-info/WHEEL
rubin_jupyter_utils.hub-0.38.0.dist-info/entry_points.txt
rubin_jupyter_utils.hub-0.38.0.dist-info/top_level.txt
rubin_jupyter_utils.hub-0.38.0.dist-info/RECORD
