Metadata-Version: 2.1
Name: rubin-jupyter-utils.hub
Version: 0.38.0
Summary: UNKNOWN
Home-page: https://github.com/sqre-lsst/rubin-jupyter-hub
Author: Adam Thornton
Author-email: athornton@lsst.org
License: MIT
Keywords: rubin,jupyter,jupyterhub,hub
Platform: UNKNOWN
Classifier: Development Status :: 4 - Beta
Classifier: Programming Language :: Python :: 3.6
Classifier: License :: OSI Approved :: MIT License
Requires-Dist: requests (<3,>=2)
Requires-Dist: kubernetes (>=11)
Requires-Dist: semver (<3,>=2)
Requires-Dist: oauthenticator (<1.0,>=0.9)
Requires-Dist: jupyter-client (<7,>=6)
Requires-Dist: jupyterhub-jwtauthenticator (<1.0,>=0.1)
Requires-Dist: jupyterhub-kubespawner (<1.0,>=0.13)
Requires-Dist: jinja2 (<3,>=2)
Requires-Dist: pytz (>=2020)
Requires-Dist: eliot (<2,>=1)
Requires-Dist: eliot-tree (<20,>=19)
Requires-Dist: argo-workflows (<4.0,>=3.2)
Requires-Dist: asgiref (<4,>=3)
Requires-Dist: pyyaml (>=5)
Requires-Dist: rubin-jupyter-utils.helpers (<1.0,>=0.33.0)
Requires-Dist: rubin-jupyter-utils.config (<1.0,>=0.33.0)
